bumpversion/__init__.py
bumpversion/__main__.py
bumpversion/aliases.py
bumpversion/autocast.py
bumpversion/bump.py
bumpversion/cli.py
bumpversion/click_config.py
bumpversion/context.py
bumpversion/exceptions.py
bumpversion/files.py
bumpversion/hooks.py
bumpversion/indented_logger.py
bumpversion/show.py
bumpversion/ui.py
bumpversion/utils.py
bumpversion/visualize.py
bumpversion/yaml_dump.py
bumpversion/config/__init__.py
bumpversion/config/create.py
bumpversion/config/files.py
bumpversion/config/files_legacy.py
bumpversion/config/models.py
bumpversion/config/utils.py
bumpversion/scm/__init__.py
bumpversion/scm/git.py
bumpversion/scm/hg.py
bumpversion/scm/models.py
bumpversion/versioning/__init__.py
bumpversion/versioning/conventions.py
bumpversion/versioning/functions.py
bumpversion/versioning/models.py
bumpversion/versioning/serialization.py
bumpversion/versioning/version_config.py
bump_my_version-1.2.6.dist-info/METADATA
bump_my_version-1.2.6.dist-info/WHEEL
bump_my_version-1.2.6.dist-info/entry_points.txt
bump_my_version-1.2.6.dist-info/licenses/LICENSE
bump_my_version-1.2.6.dist-info/RECORD
