Metadata-Version: 2.4
Name: bump-my-version
Version: 1.2.6
Summary: Version bump your Python project
Project-URL: homepage, https://github.com/callowayproject/bump-my-version
Project-URL: repository, https://github.com/callowayproject/bump-my-version.git
Project-URL: documentation, https://callowayproject.github.io/bump-my-version/
Author-email: Corey Oordt <coreyoordt@gmail.com>
License: MIT License
License-File: LICENSE
Keywords: bumpversion,release,version
Classifier: Development Status :: 5 - Production/Stable
Classifier: Environment :: Console
Classifier: Intended Audience :: Developers
Classifier: License :: OSI Approved :: MIT License
Classifier: Operating System :: OS Independent
Classifier: Programming Language :: Python
Classifier: Programming Language :: Python :: 3 :: Only
Classifier: Programming Language :: Python :: 3.8
Classifier: Programming Language :: Python :: 3.9
Classifier: Programming Language :: Python :: 3.10
Classifier: Programming Language :: Python :: 3.11
Classifier: Programming Language :: Python :: 3.12
Classifier: Programming Language :: Python :: 3.13
Classifier: Programming Language :: Python :: Implementation :: PyPy
Classifier: Topic :: Software Development :: Build Tools
Classifier: Topic :: Software Development :: Version Control
Classifier: Topic :: System :: Software Distribution
Requires-Python: >=3.8
Requires-Dist: click<8.4
Requires-Dist: httpx>=0.28.1
Requires-Dist: pydantic-settings
Requires-Dist: pydantic>=2.0.0
Requires-Dist: questionary
Requires-Dist: rich
Requires-Dist: rich-click
Requires-Dist: tomlkit
Requires-Dist: wcmatch>=8.5.1
